pyenmeval/__init__.py
pyenmeval/data_split.py
pyenmeval/enmevaluate.py
pyenmeval/maxent_wrapper.py
pyenmeval/metrics.py
pyenmeval/utils.py
pyenmeval-0.1.3.dist-info/licenses/LICENSE
pyenmeval-0.1.3.dist-info/METADATA
pyenmeval-0.1.3.dist-info/WHEEL
pyenmeval-0.1.3.dist-info/top_level.txt
pyenmeval-0.1.3.dist-info/RECORD
